assembly_payments/__init__.py
assembly_payments/client.py
assembly_payments/exceptions.py
assembly_payments/types.py
assembly_payments/services/__init__.py
assembly_payments/services/bank_account.py
assembly_payments/services/base.py
assembly_payments/services/batch_transaction.py
assembly_payments/services/bpay_account.py
assembly_payments/services/callback.py
assembly_payments/services/company.py
assembly_payments/services/direct_debit_authority.py
assembly_payments/services/disbursement.py
assembly_payments/services/item.py
assembly_payments/services/testing.py
assembly_payments/services/token.py
assembly_payments/services/transaction.py
assembly_payments/services/user.py
assembly_payments/services/virtual_account.py
assembly_payments/services/wallet_account.py
assembly_payments/services/webhook.py
tests/utils/__init__.py
tests/utils/base.py
tests/utils/factories.py
py_assembly_payments-0.23.0.dist-info/LICENSE
py_assembly_payments-0.23.0.dist-info/METADATA
py_assembly_payments-0.23.0.dist-info/WHEEL
py_assembly_payments-0.23.0.dist-info/top_level.txt
py_assembly_payments-0.23.0.dist-info/RECORD
