Metadata-Version: 2.1
Name: py-assembly-payments
Version: 0.23.0
Summary: Python wrapper around the Assembly Payments API
Home-page: https://github.com/divipayhq/py-assembly-payments
Author: Matthew Egan <DiviPay>
License: MIT
Classifier: License :: OSI Approved :: MIT License
Classifier: Programming Language :: Python :: 3
Classifier: Programming Language :: Python :: 3.9
License-File: LICENSE
Requires-Dist: pydantic
Requires-Dist: PyJWT
Requires-Dist: requests
